{"v":"5.1.7","fr":24,"ip":0,"op":49,"w":350,"h":310,"nm":"02加载录音文件备份","ddd":0,"assets":[],"layers":[{"ddd":0,"ind":1,"ty":4,"nm":"“music3”轮廓","sr":1,"ks":{"o":{"a":1,"k":[{"i":{"x":[0.667],"y":[1]},"o":{"x":[0.167],"y":[0.167]},"n":["0p667_1_0p167_0p167"],"t":20,"s":[0],"e":[100]},{"i":{"x":[0.833],"y":[1]},"o":{"x":[0.333],"y":[0]},"n":["0p833_1_0p333_0"],"t":25,"s":[100],"e":[100]},{"i":{"x":[0.667],"y":[1]},"o":{"x":[0.167],"y":[0.167]},"n":["0p667_1_0p167_0p167"],"t":31,"s":[100],"e":[0]},{"t":36}],"ix":11},"r":{"a":0,"k":0,"ix":10},"p":{"a":0,"k":[317,69,0],"ix":2},"a":{"a":0,"k":[28,27,0],"ix":1},"s":{"a":0,"k":[100,100,100],"ix":6}},"ao":0,"shapes":[{"ty":"gr","it":[{"ind":0,"ty":"sh","ix":1,"ks":{"a":0,"k":{"i":[[0,0],[1.095,-0.919],[3.749,4.468],[-3.909,3.28],[-3.749,-4.468],[-0.407,-0.809],[0,0],[0,0],[0,0],[-1.333,-1.202],[-0.097,-0.115],[0,0],[1.068,-1.205],[0,0],[0,0],[0.903,-0.807],[0,0],[3.749,4.468],[-3.909,3.28],[-3.749,-4.468],[-0.415,-0.847],[0,0],[0,0]],"o":[[-0.5,1.283],[-3.909,3.28],[-3.749,-4.468],[3.909,-3.28],[0.615,0.733],[0,0],[0,0],[0,0],[1.202,-1.332],[0.112,0.101],[0,0],[1.035,1.233],[0,0],[0,0],[-0.47,1.075],[0,0],[-3.909,3.28],[-3.749,-4.468],[3.909,-3.28],[0.642,0.764],[0,0],[0,0],[0,0]],"v":[[-8.875,0.59],[-11.267,3.945],[-25.133,1.795],[-24.843,-12.233],[-10.977,-10.083],[-9.445,-7.76],[1.5,-21.236],[1.416,-21.335],[5.163,-25.488],[9.752,-25.724],[10.065,-25.4],[27.102,-5.096],[27.045,-0.853],[24.621,1.882],[8.332,21.589],[6.271,24.445],[6.076,24.614],[-7.79,22.464],[-7.5,8.435],[6.366,10.585],[7.95,13.014],[19.05,-0.321],[4.981,-17.087]],"c":true},"ix":2},"nm":"路径 1","mn":"ADBE Vector Shape - Group","hd":false},{"ty":"mm","mm":4,"nm":"合并路径 1","mn":"ADBE Vector Filter - Merge","hd":false},{"ty":"fl","c":{"a":0,"k":[0.572549019608,0.921568627451,0.58431372549,1],"ix":4},"o":{"a":0,"k":100,"ix":5},"r":1,"nm":"填充 1","mn":"ADBE Vector Graphic - Fill","hd":false},{"ty":"tr","p":{"a":0,"k":[27.862,27.439],"ix":2},"a":{"a":0,"k":[0,0],"ix":1},"s":{"a":0,"k":[100,100],"ix":3},"r":{"a":0,"k":0,"ix":6},"o":{"a":0,"k":100,"ix":7},"sk":{"a":0,"k":0,"ix":4},"sa":{"a":0,"k":0,"ix":5},"nm":"变换"}],"nm":"组 1","np":4,"cix":2,"ix":1,"mn":"ADBE Vector Group","hd":false}],"ip":0,"op":14415.2152152152,"st":0,"bm":0},{"ddd":0,"ind":2,"ty":4,"nm":"“music2”轮廓","sr":1,"ks":{"o":{"a":1,"k":[{"i":{"x":[0.667],"y":[1]},"o":{"x":[0.167],"y":[0.167]},"n":["0p667_1_0p167_0p167"],"t":10,"s":[0],"e":[100]},{"i":{"x":[0.833],"y":[1]},"o":{"x":[0.333],"y":[0]},"n":["0p833_1_0p333_0"],"t":15,"s":[100],"e":[100]},{"i":{"x":[0.667],"y":[1]},"o":{"x":[0.167],"y":[0.167]},"n":["0p667_1_0p167_0p167"],"t":31,"s":[100],"e":[0]},{"t":36}],"ix":11},"r":{"a":0,"k":0,"ix":10},"p":{"a":0,"k":[179,23.75,0],"ix":2},"a":{"a":0,"k":[24,20,0],"ix":1},"s":{"a":0,"k":[100,100,100],"ix":6}},"ao":0,"shapes":[{"ty":"gr","it":[{"ind":0,"ty":"sh","ix":1,"ks":{"a":0,"k":{"i":[[7.23,0],[0,-8.591],[-7.23,0],[0,8.591]],"o":[[-7.23,0],[0,8.591],[7.23,0],[0,-8.591]],"v":[[0,-15.556],[-13.091,0],[0,15.556],[13.091,0]],"c":true},"ix":2},"nm":"路径 1","mn":"ADBE Vector Shape - Group","hd":false},{"ind":1,"ty":"sh","ix":2,"ks":{"a":0,"k":{"i":[[-13.255,0],[0,-11.046],[13.255,0],[0,11.046]],"o":[[13.255,0],[0,11.046],[-13.255,0],[0,-11.046]],"v":[[0,-20],[24,0],[0,20],[-24,0]],"c":true},"ix":2},"nm":"路径 2","mn":"ADBE Vector Shape - Group","hd":false},{"ty":"mm","mm":1,"nm":"合并路径 1","mn":"ADBE Vector Filter - Merge","hd":false},{"ty":"fl","c":{"a":0,"k":[0.964705882353,0.41568627451,0.243137254902,1],"ix":4},"o":{"a":0,"k":100,"ix":5},"r":1,"nm":"填充 1","mn":"ADBE Vector Graphic - Fill","hd":false},{"ty":"tr","p":{"a":0,"k":[24,20],"ix":2},"a":{"a":0,"k":[0,0],"ix":1},"s":{"a":0,"k":[100,100],"ix":3},"r":{"a":0,"k":0,"ix":6},"o":{"a":0,"k":100,"ix":7},"sk":{"a":0,"k":0,"ix":4},"sa":{"a":0,"k":0,"ix":5},"nm":"变换"}],"nm":"组 1","np":4,"cix":2,"ix":1,"mn":"ADBE Vector Group","hd":false}],"ip":0,"op":14415.2152152152,"st":0,"bm":0},{"ddd":0,"ind":3,"ty":4,"nm":"“music1”轮廓","sr":1,"ks":{"o":{"a":1,"k":[{"i":{"x":[0.667],"y":[1]},"o":{"x":[0.167],"y":[0.167]},"n":["0p667_1_0p167_0p167"],"t":0,"s":[0],"e":[100]},{"i":{"x":[0.833],"y":[1]},"o":{"x":[0.333],"y":[0]},"n":["0p833_1_0p333_0"],"t":5,"s":[100],"e":[100]},{"i":{"x":[0.667],"y":[1]},"o":{"x":[0.167],"y":[0.167]},"n":["0p667_1_0p167_0p167"],"t":31,"s":[100],"e":[0]},{"t":36}],"ix":11},"r":{"a":0,"k":0,"ix":10},"p":{"a":0,"k":[42.5,68.5,0],"ix":2},"a":{"a":0,"k":[16,29.5,0],"ix":1},"s":{"a":0,"k":[100,100,100],"ix":6}},"ao":0,"shapes":[{"ty":"gr","it":[{"ind":0,"ty":"sh","ix":1,"ks":{"a":0,"k":{"i":[[0,0],[4.012,-3.134],[0,0],[0,0],[1.908,-4.731],[-5.136,-2.08],[-2.482,6.167],[2.204,3.069],[0,0],[0,0]],"o":[[-4.605,-2.19],[0,0],[0,0],[-4.118,0.226],[-2.486,6.161],[5.136,2.08],[1.729,-4.287],[0,0],[0,0],[0,0]],"v":[[8.24,-27.921],[-5.819,-26.38],[-15.699,-18.661],[4.392,7.054],[-4.61,14.569],[0.864,28.606],[14.669,21.208],[13.67,9.323],[13.636,9.266],[-6.452,-16.443]],"c":true},"ix":2},"nm":"路径 1","mn":"ADBE Vector Shape - Group","hd":false},{"ty":"mm","mm":4,"nm":"合并路径 1","mn":"ADBE Vector Filter - Merge","hd":false},{"ty":"fl","c":{"a":0,"k":[0.509803921569,0.592156862745,0.960784313725,1],"ix":4},"o":{"a":0,"k":100,"ix":5},"r":1,"nm":"填充 1","mn":"ADBE Vector Graphic - Fill","hd":false},{"ty":"tr","p":{"a":0,"k":[14.199,28.523],"ix":2},"a":{"a":0,"k":[0,0],"ix":1},"s":{"a":0,"k":[100,100],"ix":3},"r":{"a":0,"k":0,"ix":6},"o":{"a":0,"k":100,"ix":7},"sk":{"a":0,"k":0,"ix":4},"sa":{"a":0,"k":0,"ix":5},"nm":"变换"}],"nm":"组 1","np":4,"cix":2,"ix":1,"mn":"ADBE Vector Group","hd":false}],"ip":0,"op":14415.2152152152,"st":0,"bm":0},{"ddd":0,"ind":4,"ty":4,"nm":"“eye2”轮廓 2","sr":1,"ks":{"o":{"a":0,"k":100,"ix":11},"r":{"a":0,"k":0,"ix":10},"p":{"a":1,"k":[{"i":{"x":0.667,"y":1},"o":{"x":0.167,"y":0.167},"n":"0p667_1_0p167_0p167","t":0,"s":[132,144.75,0],"e":[128.25,139.5,0],"to":[0,0,0],"ti":[0,0,0]},{"i":{"x":0.833,"y":0.833},"o":{"x":0.333,"y":0.333},"n":"0p833_0p833_0p333_0p333","t":5,"s":[128.25,139.5,0],"e":[128.25,139.5,0],"to":[0,0,0],"ti":[0,0,0]},{"i":{"x":0.667,"y":1},"o":{"x":0.167,"y":0.167},"n":"0p667_1_0p167_0p167","t":10,"s":[128.25,139.5,0],"e":[131.25,137.5,0],"to":[0.5,-0.33333334326744,0],"ti":[-0.5,0.33333334326744,0]},{"i":{"x":0.833,"y":0.833},"o":{"x":0.333,"y":0.333},"n":"0p833_0p833_0p333_0p333","t":15,"s":[131.25,137.5,0],"e":[131.25,137.5,0],"to":[0,0,0],"ti":[0,0,0]},{"i":{"x":0.667,"y":1},"o":{"x":0.167,"y":0.167},"n":"0p667_1_0p167_0p167","t":20,"s":[131.25,137.5,0],"e":[134.5,137,0],"to":[0.54166668653488,-0.08333333581686,0],"ti":[-0.54166668653488,0.08333333581686,0]},{"i":{"x":0.667,"y":0.667},"o":{"x":0.333,"y":0.333},"n":"0p667_0p667_0p333_0p333","t":25,"s":[134.5,137,0],"e":[134.5,137,0],"to":[0,0,0],"ti":[0,0,0]},{"i":{"x":0.833,"y":0.833},"o":{"x":0.333,"y":0},"n":"0p833_0p833_0p333_0","t":36,"s":[134.5,137,0],"e":[132,144.75,0],"to":[-0.41666665673256,1.29166662693024,0],"ti":[0,0,0]},{"t":47}],"ix":2},"a":{"a":0,"k":[6,6,0],"ix":1},"s":{"a":0,"k":[100,100,100],"ix":6}},"ao":0,"shapes":[{"ty":"gr","it":[{"ind":0,"ty":"sh","ix":1,"ks":{"a":0,"k":{"i":[[3.141,0],[0,0],[0,-3.141],[0,0],[-3.141,0],[0,0],[0,3.141],[0,0]],"o":[[0,0],[-3.141,0],[0,0],[0,3.141],[0,0],[3.141,0],[0,0],[0,-3.141]],"v":[[0,-5.687],[0,-5.687],[-5.687,0],[-5.687,0],[0,5.687],[0,5.687],[5.687,0],[5.687,0]],"c":true},"ix":2},"nm":"路径 1","mn":"ADBE Vector Shape - Group","hd":false},{"ty":"fl","c":{"a":0,"k":[0.133574362362,0.12776963477,0.2051806132,1],"ix":4},"o":{"a":0,"k":100,"ix":5},"r":1,"nm":"填充 1","mn":"ADBE Vector Graphic - Fill","hd":false},{"ty":"tr","p":{"a":0,"k":[5.687,6.313],"ix":2},"a":{"a":0,"k":[0,0],"ix":1},"s":{"a":0,"k":[100,100],"ix":3},"r":{"a":0,"k":0,"ix":6},"o":{"a":0,"k":100,"ix":7},"sk":{"a":0,"k":0,"ix":4},"sa":{"a":0,"k":0,"ix":5},"nm":"变换"}],"nm":"组 1","np":2,"cix":2,"ix":1,"mn":"ADBE Vector Group","hd":false}],"ip":0,"op":14415.2152152152,"st":0,"bm":0},{"ddd":0,"ind":5,"ty":4,"nm":"“eye2”轮廓","sr":1,"ks":{"o":{"a":0,"k":100,"ix":11},"r":{"a":0,"k":0,"ix":10},"p":{"a":1,"k":[{"i":{"x":0.667,"y":1},"o":{"x":0.167,"y":0.167},"n":"0p667_1_0p167_0p167","t":0,"s":[216.5,145.5,0],"e":[212.5,139.5,0],"to":[0,0,0],"ti":[0,0,0]},{"i":{"x":0.833,"y":0.833},"o":{"x":0.333,"y":0.333},"n":"0p833_0p833_0p333_0p333","t":5,"s":[212.5,139.5,0],"e":[212.5,139.5,0],"to":[0,0,0],"ti":[0,0,0]},{"i":{"x":0.667,"y":1},"o":{"x":0.167,"y":0.167},"n":"0p667_1_0p167_0p167","t":10,"s":[212.5,139.5,0],"e":[216,137.5,0],"to":[0.58333331346512,-0.33333334326744,0],"ti":[-0.58333331346512,0.33333334326744,0]},{"i":{"x":0.833,"y":0.833},"o":{"x":0.333,"y":0.333},"n":"0p833_0p833_0p333_0p333","t":15,"s":[216,137.5,0],"e":[216,137.5,0],"to":[0,0,0],"ti":[0,0,0]},{"i":{"x":0.667,"y":1},"o":{"x":0.167,"y":0.167},"n":"0p667_1_0p167_0p167","t":20,"s":[216,137.5,0],"e":[220,138,0],"to":[0.66666668653488,0.08333333581686,0],"ti":[-0.66666668653488,-0.08333333581686,0]},{"i":{"x":0.667,"y":0.667},"o":{"x":0.333,"y":0.333},"n":"0p667_0p667_0p333_0p333","t":25,"s":[220,138,0],"e":[220,138,0],"to":[0,0,0],"ti":[0,0,0]},{"i":{"x":0.833,"y":0.833},"o":{"x":0.333,"y":0},"n":"0p833_0p833_0p333_0","t":36,"s":[220,138,0],"e":[216.5,145.5,0],"to":[-0.58333331346512,1.25,0],"ti":[0,0,0]},{"t":47}],"ix":2},"a":{"a":0,"k":[6,6,0],"ix":1},"s":{"a":0,"k":[100,100,100],"ix":6}},"ao":0,"shapes":[{"ty":"gr","it":[{"ind":0,"ty":"sh","ix":1,"ks":{"a":0,"k":{"i":[[3.141,0],[0,0],[0,-3.141],[0,0],[-3.141,0],[0,0],[0,3.141],[0,0]],"o":[[0,0],[-3.141,0],[0,0],[0,3.141],[0,0],[3.141,0],[0,0],[0,-3.141]],"v":[[0,-5.687],[0,-5.687],[-5.687,0],[-5.687,0],[0,5.687],[0,5.687],[5.687,0],[5.687,0]],"c":true},"ix":2},"nm":"路径 1","mn":"ADBE Vector Shape - Group","hd":false},{"ty":"fl","c":{"a":0,"k":[0.133574362362,0.12776963477,0.2051806132,1],"ix":4},"o":{"a":0,"k":100,"ix":5},"r":1,"nm":"填充 1","mn":"ADBE Vector Graphic - Fill","hd":false},{"ty":"tr","p":{"a":0,"k":[5.687,6.313],"ix":2},"a":{"a":0,"k":[0,0],"ix":1},"s":{"a":0,"k":[100,100],"ix":3},"r":{"a":0,"k":0,"ix":6},"o":{"a":0,"k":100,"ix":7},"sk":{"a":0,"k":0,"ix":4},"sa":{"a":0,"k":0,"ix":5},"nm":"变换"}],"nm":"组 1","np":2,"cix":2,"ix":1,"mn":"ADBE Vector Group","hd":false}],"ip":0,"op":14415.2152152152,"st":0,"bm":0},{"ddd":0,"ind":6,"ty":4,"nm":"“eye1@1x”轮廓","sr":1,"ks":{"o":{"a":0,"k":100,"ix":11},"r":{"a":0,"k":0,"ix":10},"p":{"a":0,"k":[216.25,145,0],"ix":2},"a":{"a":0,"k":[14.5,14.5,0],"ix":1},"s":{"a":0,"k":[100,100,100],"ix":6}},"ao":0,"shapes":[{"ty":"gr","it":[{"ind":0,"ty":"sh","ix":1,"ks":{"a":0,"k":{"i":[[7.852,0],[0,0],[0,-7.852],[0,0],[-7.852,0],[0,0],[0,7.852],[0,0]],"o":[[0,0],[-7.852,0],[0,0],[0,7.852],[0,0],[7.852,0],[0,0],[0,-7.852]],"v":[[0,-14.217],[0,-14.217],[-14.217,0],[-14.217,0],[0,14.217],[0,14.217],[14.217,0],[14.217,0]],"c":true},"ix":2},"nm":"路径 1","mn":"ADBE Vector Shape - Group","hd":false},{"ty":"fl","c":{"a":0,"k":[0.999999940162,0.999999940162,1,1],"ix":4},"o":{"a":0,"k":100,"ix":5},"r":1,"nm":"填充 1","mn":"ADBE Vector Graphic - Fill","hd":false},{"ty":"tr","p":{"a":0,"k":[14.217,14.783],"ix":2},"a":{"a":0,"k":[0,0],"ix":1},"s":{"a":0,"k":[100,100],"ix":3},"r":{"a":0,"k":0,"ix":6},"o":{"a":0,"k":100,"ix":7},"sk":{"a":0,"k":0,"ix":4},"sa":{"a":0,"k":0,"ix":5},"nm":"变换"}],"nm":"组 1","np":2,"cix":2,"ix":1,"mn":"ADBE Vector Group","hd":false}],"ip":0,"op":14415.2152152152,"st":0,"bm":0},{"ddd":0,"ind":7,"ty":4,"nm":"“eye1@1x”轮廓 2","sr":1,"ks":{"o":{"a":0,"k":100,"ix":11},"r":{"a":0,"k":0,"ix":10},"p":{"a":0,"k":[132,145,0],"ix":2},"a":{"a":0,"k":[14.5,14.5,0],"ix":1},"s":{"a":0,"k":[100,100,100],"ix":6}},"ao":0,"shapes":[{"ty":"gr","it":[{"ind":0,"ty":"sh","ix":1,"ks":{"a":0,"k":{"i":[[7.852,0],[0,0],[0,-7.852],[0,0],[-7.852,0],[0,0],[0,7.852],[0,0]],"o":[[0,0],[-7.852,0],[0,0],[0,7.852],[0,0],[7.852,0],[0,0],[0,-7.852]],"v":[[0,-14.217],[0,-14.217],[-14.217,0],[-14.217,0],[0,14.217],[0,14.217],[14.217,0],[14.217,0]],"c":true},"ix":2},"nm":"路径 1","mn":"ADBE Vector Shape - Group","hd":false},{"ty":"fl","c":{"a":0,"k":[0.999999940162,0.999999940162,1,1],"ix":4},"o":{"a":0,"k":100,"ix":5},"r":1,"nm":"填充 1","mn":"ADBE Vector Graphic - Fill","hd":false},{"ty":"tr","p":{"a":0,"k":[14.217,14.783],"ix":2},"a":{"a":0,"k":[0,0],"ix":1},"s":{"a":0,"k":[100,100],"ix":3},"r":{"a":0,"k":0,"ix":6},"o":{"a":0,"k":100,"ix":7},"sk":{"a":0,"k":0,"ix":4},"sa":{"a":0,"k":0,"ix":5},"nm":"变换"}],"nm":"组 1","np":2,"cix":2,"ix":1,"mn":"ADBE Vector Group","hd":false}],"ip":0,"op":14415.2152152152,"st":0,"bm":0},{"ddd":0,"ind":8,"ty":4,"nm":"“mouth”轮廓","sr":1,"ks":{"o":{"a":0,"k":100,"ix":11},"r":{"a":0,"k":0,"ix":10},"p":{"a":0,"k":[173,188,0],"ix":2},"a":{"a":0,"k":[23.5,23.5,0],"ix":1},"s":{"a":1,"k":[{"i":{"x":[0.667,0.667,0.667],"y":[1,1,1]},"o":{"x":[0.333,0.333,0.333],"y":[0,0,0]},"n":["0p667_1_0p333_0","0p667_1_0p333_0","0p667_1_0p333_0"],"t":0,"s":[100,100,100],"e":[100,90,100]},{"i":{"x":[0.667,0.667,0.667],"y":[1,1,1]},"o":{"x":[0.333,0.333,0.333],"y":[0,0,0]},"n":["0p667_1_0p333_0","0p667_1_0p333_0","0p667_1_0p333_0"],"t":12,"s":[100,90,100],"e":[100,100,100]},{"i":{"x":[0.667,0.667,0.667],"y":[1,1,1]},"o":{"x":[0.333,0.333,0.333],"y":[0,0,0]},"n":["0p667_1_0p333_0","0p667_1_0p333_0","0p667_1_0p333_0"],"t":24,"s":[100,100,100],"e":[100,90,100]},{"i":{"x":[0.667,0.667,0.667],"y":[1,1,1]},"o":{"x":[0.333,0.333,0.333],"y":[0,0,0]},"n":["0p667_1_0p333_0","0p667_1_0p333_0","0p667_1_0p333_0"],"t":36,"s":[100,90,100],"e":[100,100,100]},{"i":{"x":[0.667,0.667,0.667],"y":[1,1,1]},"o":{"x":[0.333,0.333,0.333],"y":[0,0,0]},"n":["0p667_1_0p333_0","0p667_1_0p333_0","0p667_1_0p333_0"],"t":48,"s":[100,100,100],"e":[100,90,100]},{"i":{"x":[0.667,0.667,0.667],"y":[1,1,1]},"o":{"x":[0.333,0.333,0.333],"y":[0,0,0]},"n":["0p667_1_0p333_0","0p667_1_0p333_0","0p667_1_0p333_0"],"t":60,"s":[100,90,100],"e":[100,100,100]},{"t":72}],"ix":6}},"ao":0,"shapes":[{"ty":"gr","it":[{"ind":0,"ty":"sh","ix":1,"ks":{"a":0,"k":{"i":[[10.993,0],[0,-10.993],[-10.993,0],[0,10.993]],"o":[[-10.993,0],[0,10.993],[10.993,0],[0,-10.993]],"v":[[0,-19.904],[-19.904,0],[0,19.904],[19.904,0]],"c":true},"ix":2},"nm":"路径 1","mn":"ADBE Vector Shape - Group","hd":false},{"ty":"st","c":{"a":0,"k":[0.996078431373,0.435294117647,0.482352941176,1],"ix":3},"o":{"a":0,"k":100,"ix":4},"w":{"a":0,"k":7.109,"ix":5},"lc":1,"lj":1,"ml":4,"nm":"描边 1","mn":"ADBE Vector Graphic - Stroke","hd":false},{"ty":"fl","c":{"a":0,"k":[0.501960784314,0.070588235294,0.164705882353,1],"ix":4},"o":{"a":0,"k":100,"ix":5},"r":1,"nm":"填充 1","mn":"ADBE Vector Graphic - Fill","hd":false},{"ty":"tr","p":{"a":0,"k":[23.458,23.542],"ix":2},"a":{"a":0,"k":[0,0],"ix":1},"s":{"a":0,"k":[100,100],"ix":3},"r":{"a":0,"k":0,"ix":6},"o":{"a":0,"k":100,"ix":7},"sk":{"a":0,"k":0,"ix":4},"sa":{"a":0,"k":0,"ix":5},"nm":"变换"}],"nm":"组 1","np":3,"cix":2,"ix":1,"mn":"ADBE Vector Group","hd":false}],"ip":0,"op":14415.2152152152,"st":0,"bm":0},{"ddd":0,"ind":9,"ty":4,"nm":"“hand1”轮廓 2","sr":1,"ks":{"o":{"a":0,"k":100,"ix":11},"r":{"a":0,"k":0,"ix":10},"p":{"a":1,"k":[{"i":{"x":0.667,"y":1},"o":{"x":0.333,"y":0},"n":"0p667_1_0p333_0","t":0,"s":[90,215,0],"e":[90,210,0],"to":[0,-0.83333331346512,0],"ti":[0,0,0]},{"i":{"x":0.667,"y":1},"o":{"x":0.333,"y":0},"n":"0p667_1_0p333_0","t":12,"s":[90,210,0],"e":[90,215,0],"to":[0,0,0],"ti":[0,0,0]},{"i":{"x":0.667,"y":1},"o":{"x":0.333,"y":0},"n":"0p667_1_0p333_0","t":24,"s":[90,215,0],"e":[90,210,0],"to":[0,0,0],"ti":[0,0,0]},{"i":{"x":0.667,"y":1},"o":{"x":0.333,"y":0},"n":"0p667_1_0p333_0","t":36,"s":[90,210,0],"e":[90,215,0],"to":[0,0,0],"ti":[0,0,0]},{"i":{"x":0.667,"y":1},"o":{"x":0.333,"y":0},"n":"0p667_1_0p333_0","t":48,"s":[90,215,0],"e":[90,210,0],"to":[0,0,0],"ti":[0,0,0]},{"i":{"x":0.667,"y":1},"o":{"x":0.333,"y":0},"n":"0p667_1_0p333_0","t":60,"s":[90,210,0],"e":[90,215,0],"to":[0,0,0],"ti":[0,-0.83333331346512,0]},{"t":72}],"ix":2},"a":{"a":0,"k":[16.5,17,0],"ix":1},"s":{"a":0,"k":[100,100,100],"ix":6}},"ao":0,"shapes":[{"ty":"gr","it":[{"ind":0,"ty":"sh","ix":1,"ks":{"a":0,"k":{"i":[[9.008,0],[0,-9.209],[-9.008,0],[0,9.209]],"o":[[-9.008,0],[0,9.209],[9.008,0],[0,-9.209]],"v":[[0,-16.674],[-16.311,0],[0,16.674],[16.311,0]],"c":true},"ix":2},"nm":"路径 1","mn":"ADBE Vector Shape - Group","hd":false},{"ty":"fl","c":{"a":0,"k":[0.839215686275,0.878431372549,0.898039215686,1],"ix":4},"o":{"a":0,"k":100,"ix":5},"r":1,"nm":"填充 1","mn":"ADBE Vector Graphic - Fill","hd":false},{"ty":"tr","p":{"a":0,"k":[16.311,17.326],"ix":2},"a":{"a":0,"k":[0,0],"ix":1},"s":{"a":0,"k":[100,100],"ix":3},"r":{"a":0,"k":0,"ix":6},"o":{"a":0,"k":100,"ix":7},"sk":{"a":0,"k":0,"ix":4},"sa":{"a":0,"k":0,"ix":5},"nm":"变换"}],"nm":"组 1","np":2,"cix":2,"ix":1,"mn":"ADBE Vector Group","hd":false}],"ip":0,"op":14415.2152152152,"st":0,"bm":0},{"ddd":0,"ind":10,"ty":4,"nm":"“hand1”轮廓","sr":1,"ks":{"o":{"a":0,"k":100,"ix":11},"r":{"a":0,"k":0,"ix":10},"p":{"a":1,"k":[{"i":{"x":0.667,"y":1},"o":{"x":0.333,"y":0},"n":"0p667_1_0p333_0","t":0,"s":[262,214,0],"e":[262,204,0],"to":[0,-1.66666662693024,0],"ti":[0,0,0]},{"i":{"x":0.667,"y":1},"o":{"x":0.333,"y":0},"n":"0p667_1_0p333_0","t":12,"s":[262,204,0],"e":[262,214,0],"to":[0,0,0],"ti":[0,0,0]},{"i":{"x":0.667,"y":1},"o":{"x":0.333,"y":0},"n":"0p667_1_0p333_0","t":24,"s":[262,214,0],"e":[262,204,0],"to":[0,0,0],"ti":[0,0,0]},{"i":{"x":0.667,"y":1},"o":{"x":0.333,"y":0},"n":"0p667_1_0p333_0","t":36,"s":[262,204,0],"e":[262,214,0],"to":[0,0,0],"ti":[0,0,0]},{"i":{"x":0.667,"y":1},"o":{"x":0.333,"y":0},"n":"0p667_1_0p333_0","t":48,"s":[262,214,0],"e":[262,204,0],"to":[0,0,0],"ti":[0,0,0]},{"i":{"x":0.667,"y":1},"o":{"x":0.333,"y":0},"n":"0p667_1_0p333_0","t":60,"s":[262,204,0],"e":[262,214,0],"to":[0,0,0],"ti":[0,-1.66666662693024,0]},{"t":72}],"ix":2},"a":{"a":0,"k":[16.5,17,0],"ix":1},"s":{"a":0,"k":[100,100,100],"ix":6}},"ao":0,"shapes":[{"ty":"gr","it":[{"ind":0,"ty":"sh","ix":1,"ks":{"a":0,"k":{"i":[[9.008,0],[0,-9.209],[-9.008,0],[0,9.209]],"o":[[-9.008,0],[0,9.209],[9.008,0],[0,-9.209]],"v":[[0,-16.674],[-16.311,0],[0,16.674],[16.311,0]],"c":true},"ix":2},"nm":"路径 1","mn":"ADBE Vector Shape - Group","hd":false},{"ty":"fl","c":{"a":0,"k":[0.839215686275,0.878431372549,0.898039215686,1],"ix":4},"o":{"a":0,"k":100,"ix":5},"r":1,"nm":"填充 1","mn":"ADBE Vector Graphic - Fill","hd":false},{"ty":"tr","p":{"a":0,"k":[16.311,17.326],"ix":2},"a":{"a":0,"k":[0,0],"ix":1},"s":{"a":0,"k":[100,100],"ix":3},"r":{"a":0,"k":0,"ix":6},"o":{"a":0,"k":100,"ix":7},"sk":{"a":0,"k":0,"ix":4},"sa":{"a":0,"k":0,"ix":5},"nm":"变换"}],"nm":"组 1","np":2,"cix":2,"ix":1,"mn":"ADBE Vector Group","hd":false}],"ip":0,"op":14415.2152152152,"st":0,"bm":0},{"ddd":0,"ind":11,"ty":4,"nm":"形状图层 1","sr":1,"ks":{"o":{"a":0,"k":100,"ix":11},"r":{"a":0,"k":0,"ix":10},"p":{"a":0,"k":[175,155.5,0],"ix":2},"a":{"a":0,"k":[0,0,0],"ix":1},"s":{"a":0,"k":[100,100,100],"ix":6}},"ao":0,"shapes":[{"ty":"gr","it":[{"ty":"rc","d":1,"s":{"a":0,"k":[166,160],"ix":2},"p":{"a":0,"k":[0,0],"ix":3},"r":{"a":0,"k":27,"ix":4},"nm":"矩形路径 1","mn":"ADBE Vector Shape - Rect","hd":false},{"ty":"st","c":{"a":0,"k":[0.850980392157,0.890196078431,0.909803921569,1],"ix":3},"o":{"a":0,"k":100,"ix":4},"w":{"a":0,"k":3,"ix":5},"lc":1,"lj":1,"ml":4,"nm":"描边 1","mn":"ADBE Vector Graphic - Stroke","hd":false},{"ty":"tr","p":{"a":0,"k":[-1.557,19.838],"ix":2},"a":{"a":0,"k":[0,0],"ix":1},"s":{"a":0,"k":[100,100],"ix":3},"r":{"a":0,"k":0,"ix":6},"o":{"a":0,"k":100,"ix":7},"sk":{"a":0,"k":0,"ix":4},"sa":{"a":0,"k":0,"ix":5},"nm":"变换"}],"nm":"矩形 1","np":3,"cix":2,"ix":1,"mn":"ADBE Vector Group","hd":false}],"ip":0,"op":14419,"st":0,"bm":0},{"ddd":0,"ind":12,"ty":4,"nm":"“face2”轮廓","sr":1,"ks":{"o":{"a":0,"k":100,"ix":11},"r":{"a":0,"k":0,"ix":10},"p":{"a":0,"k":[175,158.5,0],"ix":2},"a":{"a":0,"k":[51.5,63.5,0],"ix":1},"s":{"a":0,"k":[100,100,100],"ix":6}},"ao":0,"shapes":[{"ty":"gr","it":[{"ind":0,"ty":"sh","ix":1,"ks":{"a":0,"k":{"i":[[7.067,0],[0,0],[0,7.067],[0,0],[0,0],[0,0]],"o":[[0,0],[-7.067,0],[0,0],[0,0],[0,0],[0,7.067]],"v":[[38.386,63.267],[-38.386,63.267],[-51.181,50.47],[-51.181,-63.267],[51.181,-63.267],[51.181,50.47]],"c":true},"ix":2},"nm":"路径 1","mn":"ADBE Vector Shape - Group","hd":false},{"ind":1,"ty":"sh","ix":2,"ks":{"a":0,"k":{"i":[[0,0],[0,0],[0,0],[0,0]],"o":[[0,0],[0,0],[0,0],[0,0]],"v":[[-36.963,-63.266],[-36.963,49.048],[36.966,49.048],[36.966,-63.266]],"c":true},"ix":2},"nm":"路径 2","mn":"ADBE Vector Shape - Group","hd":false},{"ty":"mm","mm":1,"nm":"合并路径 1","mn":"ADBE Vector Filter - Merge","hd":false},{"ty":"fl","c":{"a":0,"k":[0.850980392157,0.890196078431,0.909803921569,1],"ix":4},"o":{"a":0,"k":100,"ix":5},"r":1,"nm":"填充 1","mn":"ADBE Vector Graphic - Fill","hd":false},{"ty":"tr","p":{"a":0,"k":[51.181,63.733],"ix":2},"a":{"a":0,"k":[0,0],"ix":1},"s":{"a":0,"k":[100,100],"ix":3},"r":{"a":0,"k":0,"ix":6},"o":{"a":0,"k":100,"ix":7},"sk":{"a":0,"k":0,"ix":4},"sa":{"a":0,"k":0,"ix":5},"nm":"变换"}],"nm":"组 1","np":4,"cix":2,"ix":1,"mn":"ADBE Vector Group","hd":false}],"ip":0,"op":14415.2152152152,"st":0,"bm":0},{"ddd":0,"ind":13,"ty":4,"nm":"“face1”轮廓","sr":1,"ks":{"o":{"a":0,"k":100,"ix":11},"r":{"a":0,"k":0,"ix":10},"p":{"a":0,"k":[173.5,174.5,0],"ix":2},"a":{"a":0,"k":[84,80,0],"ix":1},"s":{"a":0,"k":[100,100,100],"ix":6}},"ao":0,"shapes":[{"ty":"gr","it":[{"ind":0,"ty":"sh","ix":1,"ks":{"a":0,"k":{"i":[[12.563,0],[0,0],[0,12.563],[0,0],[-12.563,0],[0,0],[0,0],[0,0],[3.814,-3.811],[0.001,-5.817],[0,0],[-3.811,-3.814],[-5.817,-0.001],[0,0],[-3.814,3.812],[-0.001,5.817],[0,0],[3.811,3.814],[5.817,0.001],[0,0],[0,-12.563],[0,0]],"o":[[0,0],[-12.563,0],[0,0],[0,-12.563],[0,0],[0,0],[0,0],[-5.817,0.001],[-3.811,3.814],[0,0],[0.001,5.817],[3.814,3.812],[0,0],[5.817,-0.001],[3.811,-3.814],[0,0],[-0.001,-5.817],[-3.814,-3.811],[0,0],[12.563,0],[0,0],[0,12.563]],"v":[[59.433,77.915],[-59.433,77.915],[-82.18,55.167],[-82.18,-55.168],[-59.433,-77.915],[59.433,-77.915],[59.433,-76.214],[-59.433,-76.214],[-74.315,-70.05],[-80.479,-55.168],[-80.479,55.167],[-74.315,70.049],[-59.433,76.214],[59.433,76.214],[74.315,70.049],[80.479,55.167],[80.479,-55.168],[74.315,-70.05],[59.433,-76.214],[59.433,-77.915],[82.18,-55.168],[82.18,55.167]],"c":true},"ix":2},"nm":"路径 1","mn":"ADBE Vector Shape - Group","hd":false},{"ty":"fl","c":{"a":0,"k":[0.929411764706,0.945098039216,0.949019607843,1],"ix":4},"o":{"a":0,"k":100,"ix":5},"r":1,"nm":"填充 1","mn":"ADBE Vector Graphic - Fill","hd":false},{"ty":"tr","p":{"a":0,"k":[83.881,80.384],"ix":2},"a":{"a":0,"k":[0,0],"ix":1},"s":{"a":0,"k":[100,100],"ix":3},"r":{"a":0,"k":0,"ix":6},"o":{"a":0,"k":100,"ix":7},"sk":{"a":0,"k":0,"ix":4},"sa":{"a":0,"k":0,"ix":5},"nm":"变换"}],"nm":"组 1","np":2,"cix":2,"ix":1,"mn":"ADBE Vector Group","hd":false},{"ty":"gr","it":[{"ind":0,"ty":"sh","ix":1,"ks":{"a":0,"k":{"i":[[13.503,-0.002],[0,0],[0.001,13.503],[0,0],[-13.503,0.001],[0,0],[0,0],[0,0],[0,-12.563],[0,0],[-12.563,0],[0,0],[0,12.563],[0,0],[12.563,0],[0,0],[-0.001,-13.503],[0,0]],"o":[[0,0],[-13.503,-0.002],[0,0],[0.001,-13.503],[0,0],[0,0],[0,0],[-12.563,0],[0,0],[0,12.563],[0,0],[12.563,0],[0,0],[0,-12.563],[0,0],[13.503,0.001],[0,0],[-0.001,13.503]],"v":[[59.433,79.616],[-59.433,79.616],[-83.881,55.167],[-83.881,-55.168],[-59.433,-79.616],[59.433,-79.616],[59.433,-77.915],[-59.433,-77.915],[-82.18,-55.168],[-82.18,55.167],[-59.433,77.915],[59.433,77.915],[82.18,55.167],[82.18,-55.168],[59.433,-77.915],[59.433,-79.616],[83.881,-55.168],[83.881,55.167]],"c":true},"ix":2},"nm":"路径 1","mn":"ADBE Vector Shape - Group","hd":false},{"ty":"fl","c":{"a":0,"k":[0.850980401039,0.890196084976,0.909803926945,1],"ix":4},"o":{"a":0,"k":100,"ix":5},"r":1,"nm":"填充 1","mn":"ADBE Vector Graphic - Fill","hd":false},{"ty":"tr","p":{"a":0,"k":[83.881,80.384],"ix":2},"a":{"a":0,"k":[0,0],"ix":1},"s":{"a":0,"k":[100,100],"ix":3},"r":{"a":0,"k":0,"ix":6},"o":{"a":0,"k":100,"ix":7},"sk":{"a":0,"k":0,"ix":4},"sa":{"a":0,"k":0,"ix":5},"nm":"变换"}],"nm":"组 2","np":2,"cix":2,"ix":2,"mn":"ADBE Vector Group","hd":false},{"ty":"gr","it":[{"ind":0,"ty":"sh","ix":1,"ks":{"a":0,"k":{"i":[[12.563,0],[0,0],[0,-12.563],[0,0],[-12.563,0],[0,0],[0,12.563],[0,0]],"o":[[0,0],[-12.563,0],[0,0],[0,12.563],[0,0],[12.563,0],[0,0],[0,-12.563]],"v":[[59.433,-77.915],[-59.433,-77.915],[-82.18,-55.168],[-82.18,55.167],[-59.433,77.915],[59.433,77.915],[82.18,55.167],[82.18,-55.168]],"c":true},"ix":2},"nm":"路径 1","mn":"ADBE Vector Shape - Group","hd":false},{"ty":"fl","c":{"a":0,"k":[0.929411768913,0.945098042488,0.949019610882,1],"ix":4},"o":{"a":0,"k":100,"ix":5},"r":1,"nm":"填充 1","mn":"ADBE Vector Graphic - Fill","hd":false},{"ty":"tr","p":{"a":0,"k":[83.881,80.384],"ix":2},"a":{"a":0,"k":[0,0],"ix":1},"s":{"a":0,"k":[100,100],"ix":3},"r":{"a":0,"k":0,"ix":6},"o":{"a":0,"k":100,"ix":7},"sk":{"a":0,"k":0,"ix":4},"sa":{"a":0,"k":0,"ix":5},"nm":"变换"}],"nm":"组 3","np":2,"cix":2,"ix":3,"mn":"ADBE Vector Group","hd":false}],"ip":0,"op":14415.2152152152,"st":0,"bm":0},{"ddd":0,"ind":14,"ty":4,"nm":"“ear1”轮廓","sr":1,"ks":{"o":{"a":0,"k":100,"ix":11},"r":{"a":0,"k":0,"ix":10},"p":{"a":0,"k":[175,84,0],"ix":2},"a":{"a":0,"k":[47.5,5.5,0],"ix":1},"s":{"a":0,"k":[100,100,100],"ix":6}},"ao":0,"shapes":[{"ty":"gr","it":[{"ind":0,"ty":"sh","ix":1,"ks":{"a":0,"k":{"i":[[0,0],[0,-1.256],[0,0],[0,0],[1.256,0],[0,0],[0,0],[0,1.256],[0,0],[0,0],[-1.256,0],[0,0]],"o":[[1.256,0],[0,0],[0,0],[0,1.256],[0,0],[0,0],[-1.256,0],[0,0],[0,0],[0,-1.256],[0,0],[0,0]],"v":[[-17.558,-5.051],[-15.283,-2.776],[-15.283,-2.776],[-15.283,2.776],[-17.558,5.051],[-17.558,5.051],[-44.997,5.051],[-47.272,2.776],[-47.272,2.776],[-47.272,-2.776],[-44.997,-5.051],[-44.997,-5.051]],"c":true},"ix":2},"nm":"路径 1","mn":"ADBE Vector Shape - Group","hd":false},{"ind":1,"ty":"sh","ix":2,"ks":{"a":0,"k":{"i":[[0,0],[0,-1.256],[0,0],[0,0],[1.256,0],[0,0],[0,0],[0,1.256],[0,0],[0,0],[-1.256,0],[0,0]],"o":[[1.256,0],[0,0],[0,0],[0,1.256],[0,0],[0,0],[-1.256,0],[0,0],[0,0],[0,-1.256],[0,0],[0,0]],"v":[[44.997,-5.051],[47.272,-2.776],[47.272,-2.776],[47.272,2.776],[44.997,5.051],[44.997,5.051],[17.558,5.051],[15.283,2.776],[15.283,2.776],[15.283,-2.776],[17.558,-5.051],[17.558,-5.051]],"c":true},"ix":2},"nm":"路径 2","mn":"ADBE Vector Shape - Group","hd":false},{"ty":"mm","mm":1,"nm":"合并路径 1","mn":"ADBE Vector Filter - Merge","hd":false},{"ty":"fl","c":{"a":0,"k":[0.866666666667,0.905882352941,0.917647058824,1],"ix":4},"o":{"a":0,"k":100,"ix":5},"r":1,"nm":"填充 1","mn":"ADBE Vector Graphic - Fill","hd":false},{"ty":"tr","p":{"a":0,"k":[47.272,5.949],"ix":2},"a":{"a":0,"k":[0,0],"ix":1},"s":{"a":0,"k":[100,100],"ix":3},"r":{"a":0,"k":0,"ix":6},"o":{"a":0,"k":100,"ix":7},"sk":{"a":0,"k":0,"ix":4},"sa":{"a":0,"k":0,"ix":5},"nm":"变换"}],"nm":"组 1","np":4,"cix":2,"ix":1,"mn":"ADBE Vector Group","hd":false}],"ip":0,"op":14415.2152152152,"st":0,"bm":0},{"ddd":0,"ind":16,"ty":4,"nm":"“ear3”轮廓","sr":1,"ks":{"o":{"a":0,"k":100,"ix":11},"r":{"a":0,"k":0,"ix":10},"p":{"a":0,"k":[174.5,91.5,0],"ix":2},"a":{"a":0,"k":[41.5,5,0],"ix":1},"s":{"a":0,"k":[100,100,100],"ix":6}},"ao":0,"shapes":[{"ty":"gr","it":[{"ind":0,"ty":"sh","ix":1,"ks":{"a":0,"k":{"i":[[0,0],[0,-1.256],[0,0],[0,0],[0,0],[0,0],[-1.256,0],[0,0]],"o":[[1.256,0],[0,0],[0,0],[0,0],[0,0],[0,-1.256],[0,0],[0,0]],"v":[[-23.451,-4.005],[-21.176,-1.73],[-21.176,-1.73],[-21.176,4.716],[-41.379,4.716],[-41.379,-1.73],[-39.104,-4.005],[-39.104,-4.005]],"c":true},"ix":2},"nm":"路径 1","mn":"ADBE Vector Shape - Group","hd":false},{"ind":1,"ty":"sh","ix":2,"ks":{"a":0,"k":{"i":[[0,0],[0,-1.256],[0,0],[0,0],[0,0],[0,0],[-1.256,0],[0,0]],"o":[[1.256,0],[0,0],[0,0],[0,0],[0,0],[0,-1.256],[0,0],[0,0]],"v":[[39.105,-4.716],[41.379,-2.441],[41.379,-2.441],[41.379,4.716],[21.176,4.716],[21.176,-2.441],[23.451,-4.716],[23.451,-4.716]],"c":true},"ix":2},"nm":"路径 2","mn":"ADBE Vector Shape - Group","hd":false},{"ty":"mm","mm":1,"nm":"合并路径 1","mn":"ADBE Vector Filter - Merge","hd":false},{"ty":"fl","c":{"a":0,"k":[0.737254901961,0.803921568627,0.827450980392,1],"ix":4},"o":{"a":0,"k":100,"ix":5},"r":1,"nm":"填充 1","mn":"ADBE Vector Graphic - Fill","hd":false},{"ty":"tr","p":{"a":0,"k":[41.379,5.284],"ix":2},"a":{"a":0,"k":[0,0],"ix":1},"s":{"a":0,"k":[100,100],"ix":3},"r":{"a":0,"k":0,"ix":6},"o":{"a":0,"k":100,"ix":7},"sk":{"a":0,"k":0,"ix":4},"sa":{"a":0,"k":0,"ix":5},"nm":"变换"}],"nm":"组 1","np":4,"cix":2,"ix":1,"mn":"ADBE Vector Group","hd":false}],"ip":0,"op":14415.2152152152,"st":0,"bm":0},{"ddd":0,"ind":18,"ty":4,"nm":"“ear2”轮廓","sr":1,"ks":{"o":{"a":0,"k":100,"ix":11},"r":{"a":0,"k":0,"ix":10},"p":{"a":0,"k":[175,82.5,0],"ix":2},"a":{"a":0,"k":[41.5,11,0],"ix":1},"s":{"a":0,"k":[100,100,100],"ix":6}},"ao":0,"shapes":[{"ty":"gr","it":[{"ind":0,"ty":"sh","ix":1,"ks":{"a":0,"k":{"i":[[0,0],[0,-1.256],[0,0],[0,0],[0,0],[0,0],[-1.256,0],[0,0]],"o":[[1.256,0],[0,0],[0,0],[0,0],[0,0],[0,-1.256],[0,0],[0,0]],"v":[[-23.451,-10.853],[-21.176,-8.579],[-21.176,-8.579],[-21.176,10.853],[-41.379,10.853],[-41.379,-8.579],[-39.104,-10.853],[-39.104,-10.853]],"c":true},"ix":2},"nm":"路径 1","mn":"ADBE Vector Shape - Group","hd":false},{"ind":1,"ty":"sh","ix":2,"ks":{"a":0,"k":{"i":[[0,0],[0,-1.256],[0,0],[0,0],[0,0],[0,0],[-1.256,0],[0,0]],"o":[[1.256,0],[0,0],[0,0],[0,0],[0,0],[0,-1.256],[0,0],[0,0]],"v":[[39.105,-10.853],[41.379,-8.579],[41.379,-8.579],[41.379,10.853],[21.176,10.853],[21.176,-8.579],[23.451,-10.853],[23.451,-10.853]],"c":true},"ix":2},"nm":"路径 2","mn":"ADBE Vector Shape - Group","hd":false},{"ty":"mm","mm":1,"nm":"合并路径 1","mn":"ADBE Vector Filter - Merge","hd":false},{"ty":"fl","c":{"a":0,"k":[0.81568627451,0.866666666667,0.886274509804,1],"ix":4},"o":{"a":0,"k":100,"ix":5},"r":1,"nm":"填充 1","mn":"ADBE Vector Graphic - Fill","hd":false},{"ty":"tr","p":{"a":0,"k":[41.379,11.147],"ix":2},"a":{"a":0,"k":[0,0],"ix":1},"s":{"a":0,"k":[100,100],"ix":3},"r":{"a":0,"k":0,"ix":6},"o":{"a":0,"k":100,"ix":7},"sk":{"a":0,"k":0,"ix":4},"sa":{"a":0,"k":0,"ix":5},"nm":"变换"}],"nm":"组 1","np":4,"cix":2,"ix":1,"mn":"ADBE Vector Group","hd":false}],"ip":0,"op":14415.2152152152,"st":0,"bm":0},{"ddd":0,"ind":22,"ty":4,"nm":"“foot”轮廓","sr":1,"ks":{"o":{"a":0,"k":100,"ix":11},"r":{"a":0,"k":0,"ix":10},"p":{"a":0,"k":[174.5,279,0],"ix":2},"a":{"a":0,"k":[62,9,0],"ix":1},"s":{"a":0,"k":[100,100,100],"ix":6}},"ao":0,"shapes":[{"ty":"gr","it":[{"ind":0,"ty":"sh","ix":1,"ks":{"a":0,"k":{"i":[[-4.673,0],[-0.138,-0.007],[0,0],[0,-4.18],[0,0],[1.178,0],[0,0],[0,1.178],[0,0]],"o":[[0.138,0],[0,0],[4.175,0.204],[0,0],[0,1.178],[0,0],[-1.178,0],[0,0],[0,-4.673]],"v":[[-53.453,-8.673],[-53.039,-8.663],[-11.28,-6.619],[-3.825,1.21],[-3.825,6.541],[-5.958,8.673],[-59.781,8.673],[-61.914,6.541],[-61.914,-0.212]],"c":true},"ix":2},"nm":"路径 1","mn":"ADBE Vector Shape - Group","hd":false},{"ind":1,"ty":"sh","ix":2,"ks":{"a":0,"k":{"i":[[-0.229,-4.667],[0,-0.138],[0,0],[1.178,0],[0,0],[0,1.178],[0,0],[-4.175,0.204],[0,0]],"o":[[0.007,0.138],[0,0],[0,1.178],[0,0],[-1.178,0],[0,0],[0,-4.18],[0,0],[4.668,-0.228]],"v":[[61.904,-0.626],[61.914,-0.212],[61.914,6.541],[59.781,8.673],[5.958,8.673],[3.825,6.541],[3.825,1.21],[11.28,-6.619],[53.039,-8.663]],"c":true},"ix":2},"nm":"路径 2","mn":"ADBE Vector Shape - Group","hd":false},{"ty":"mm","mm":1,"nm":"合并路径 1","mn":"ADBE Vector Filter - Merge","hd":false},{"ty":"fl","c":{"a":0,"k":[0.326763168036,0.329445214365,0.432357070025,1],"ix":4},"o":{"a":0,"k":100,"ix":5},"r":1,"nm":"填充 1","mn":"ADBE Vector Graphic - Fill","hd":false},{"ty":"tr","p":{"a":0,"k":[61.914,9.327],"ix":2},"a":{"a":0,"k":[0,0],"ix":1},"s":{"a":0,"k":[100,100],"ix":3},"r":{"a":0,"k":0,"ix":6},"o":{"a":0,"k":100,"ix":7},"sk":{"a":0,"k":0,"ix":4},"sa":{"a":0,"k":0,"ix":5},"nm":"变换"}],"nm":"组 1","np":6,"cix":2,"ix":1,"mn":"ADBE Vector Group","hd":false}],"ip":0,"op":14415.2152152152,"st":0,"bm":0},{"ddd":0,"ind":23,"ty":4,"nm":"“leg”轮廓","sr":1,"ks":{"o":{"a":0,"k":100,"ix":11},"r":{"a":0,"k":0,"ix":10},"p":{"a":0,"k":[175,262,0],"ix":2},"a":{"a":0,"k":[44.5,12.5,0],"ix":1},"s":{"a":0,"k":[100,100,100],"ix":6}},"ao":0,"shapes":[{"ty":"gr","it":[{"ind":0,"ty":"sh","ix":1,"ks":{"a":0,"k":{"i":[[0,0],[0,0],[0,0],[0,0]],"o":[[0,0],[0,0],[0,0],[0,0]],"v":[[44.243,-12.085],[37.135,12.085],[13.677,12.085],[13.677,-12.085]],"c":true},"ix":2},"nm":"路径 1","mn":"ADBE Vector Shape - Group","hd":false},{"ind":1,"ty":"sh","ix":2,"ks":{"a":0,"k":{"i":[[0,0],[0,0],[0,0],[0,0]],"o":[[0,0],[0,0],[0,0],[0,0]],"v":[[-13.676,-12.085],[-13.676,12.085],[-37.135,12.085],[-44.243,-12.085]],"c":true},"ix":2},"nm":"路径 2","mn":"ADBE Vector Shape - Group","hd":false},{"ty":"fl","c":{"a":0,"k":[0.090196078431,0.117647058824,0.16862745098,1],"ix":4},"o":{"a":0,"k":100,"ix":5},"r":1,"nm":"填充 1","mn":"ADBE Vector Graphic - Fill","hd":false},{"ty":"tr","p":{"a":0,"k":[44.243,12.915],"ix":2},"a":{"a":0,"k":[0,0],"ix":1},"s":{"a":0,"k":[100,100],"ix":3},"r":{"a":0,"k":0,"ix":6},"o":{"a":0,"k":100,"ix":7},"sk":{"a":0,"k":0,"ix":4},"sa":{"a":0,"k":0,"ix":5},"nm":"变换"}],"nm":"组 1","np":4,"cix":2,"ix":1,"mn":"ADBE Vector Group","hd":false}],"ip":0,"op":14415.2152152152,"st":0,"bm":0},{"ddd":0,"ind":24,"ty":4,"nm":"“shadow”轮廓","sr":1,"ks":{"o":{"a":0,"k":100,"ix":11},"r":{"a":0,"k":0,"ix":10},"p":{"a":0,"k":[170.5,304.5,0],"ix":2},"a":{"a":0,"k":[91,9,0],"ix":1},"s":{"a":0,"k":[100,100,100],"ix":6}},"ao":0,"shapes":[{"ty":"gr","it":[{"ind":0,"ty":"sh","ix":1,"ks":{"a":0,"k":{"i":[[4.739,0],[0,0],[0,-4.739],[0,0],[-4.739,0],[0,0],[0,4.739],[0,0]],"o":[[0,0],[-4.739,0],[0,0],[0,4.739],[0,0],[4.739,0],[0,0],[0,-4.739]],"v":[[82.32,-8.58],[-82.32,-8.58],[-90.9,0],[-90.9,0],[-82.32,8.58],[82.32,8.58],[90.9,0],[90.9,0]],"c":true},"ix":2},"nm":"路径 1","mn":"ADBE Vector Shape - Group","hd":false},{"ty":"fl","c":{"a":0,"k":[0.835294117647,0.858823529412,0.894117647059,1],"ix":4},"o":{"a":0,"k":100,"ix":5},"r":1,"nm":"填充 1","mn":"ADBE Vector Graphic - Fill","hd":false},{"ty":"tr","p":{"a":0,"k":[94.9,-6.58],"ix":2},"a":{"a":0,"k":[0,0],"ix":1},"s":{"a":0,"k":[100,100],"ix":3},"r":{"a":0,"k":0,"ix":6},"o":{"a":0,"k":100,"ix":7},"sk":{"a":0,"k":0,"ix":4},"sa":{"a":0,"k":0,"ix":5},"nm":"变换"}],"nm":"组 1","np":2,"cix":2,"ix":1,"mn":"ADBE Vector Group","hd":false}],"ip":0,"op":14415.2152152152,"st":0,"bm":0}],"markers":[{"tm":72,"cm":"1","dr":0}]}